deformetrica/__init__.py
deformetrica/__main__.py
deformetrica/api/__init__.py
deformetrica/api/deformetrica.py
deformetrica/core/__init__.py
deformetrica/core/default.py
deformetrica/core/estimator_tools/__init__.py
deformetrica/core/estimator_tools/samplers/__init__.py
deformetrica/core/estimator_tools/samplers/srw_mhwg_sampler.py
deformetrica/core/estimators/__init__.py
deformetrica/core/estimators/abstract_estimator.py
deformetrica/core/estimators/gradient_ascent.py
deformetrica/core/estimators/mcmc_saem.py
deformetrica/core/estimators/scipy_optimize.py
deformetrica/core/model_tools/__init__.py
deformetrica/core/model_tools/attachments/__init__.py
deformetrica/core/model_tools/attachments/multi_object_attachment.py
deformetrica/core/model_tools/deformations/__init__.py
deformetrica/core/model_tools/deformations/exponential.py
deformetrica/core/model_tools/deformations/geodesic.py
deformetrica/core/model_tools/deformations/spatiotemporal_reference_frame.py
deformetrica/core/model_tools/manifolds/__init__.py
deformetrica/core/model_tools/manifolds/euclidean_exponential.py
deformetrica/core/model_tools/manifolds/exponential_factory.py
deformetrica/core/model_tools/manifolds/exponential_interface.py
deformetrica/core/model_tools/manifolds/fourier_exponential.py
deformetrica/core/model_tools/manifolds/generic_geodesic.py
deformetrica/core/model_tools/manifolds/generic_spatiotemporal_reference_frame.py
deformetrica/core/model_tools/manifolds/logistic_exponential.py
deformetrica/core/model_tools/manifolds/metric_learning_nets.py
deformetrica/core/model_tools/manifolds/parametric_exponential.py
deformetrica/core/models/__init__.py
deformetrica/core/models/abstract_statistical_model.py
deformetrica/core/models/affine_atlas.py
deformetrica/core/models/bayesian_atlas.py
deformetrica/core/models/deep_pga.py
deformetrica/core/models/deterministic_atlas.py
deformetrica/core/models/geodesic_regression.py
deformetrica/core/models/longitudinal_atlas.py
deformetrica-4.3.0.dist-info/LICENSE.txt
deformetrica-4.3.0.dist-info/METADATA
deformetrica-4.3.0.dist-info/WHEEL
deformetrica-4.3.0.dist-info/entry_points.txt
deformetrica-4.3.0.dist-info/top_level.txt
deformetrica-4.3.0.dist-info/RECORD
