Metadata-Version: 2.1
Name: deformetrica
Version: 4.3.0
Summary: Software for the statistical analysis of 2D and 3D shape data.
Home-page: http://www.deformetrica.org
Author: ARAMIS Lab
Maintainer: Deformetrica developers
Maintainer-email: deformetrica.team@gmail.com
License: INRIA license
Platform: UNKNOWN
Classifier: Development Status :: 4 - Beta
Classifier: Environment :: Console
Classifier: Environment :: X11 Applications :: Qt
Classifier: Operating System :: OS Independent
Classifier: Intended Audience :: End Users/Desktop
Classifier: Programming Language :: Python
Classifier: Programming Language :: Python :: 3
Classifier: Programming Language :: Python :: 3.6
Classifier: Programming Language :: Python :: 3.7
Classifier: Topic :: Scientific/Engineering
Classifier: Topic :: Scientific/Engineering :: Bio-Informatics
Classifier: Topic :: Software Development :: Libraries
Requires-Dist: numpy (>=1.16.2)
Requires-Dist: scikit-learn (>=0.20.3)
Requires-Dist: matplotlib (>=2.2.2)
Requires-Dist: nibabel (>=2.3.3)
Requires-Dist: pillow (>=5.4.1)
Requires-Dist: torch (==1.6)
Requires-Dist: torchvision (==0.7)
Requires-Dist: psutil (>=5.4.8)
Requires-Dist: vtk (>=8.2.0)
Requires-Dist: pykeops (==1.4.1)
Requires-Dist: PyQt5
